.gitignore
LICENSE
MANIFEST.in
README.md
setup.py
tests.py
websms.py
websms.egg-info/PKG-INFO
websms.egg-info/SOURCES.txt
websms.egg-info/dependency_links.txt
websms.egg-info/requires.txt
websms.egg-info/top_level.txt