Metadata-Version: 2.1
Name: websms
Version: 1.0.0
Summary: Python library that allows to send messages using websms platform.
Home-page: https://github.com/W-Z-FinTech-GmbH/websms
Author: W&Z FinTech GmbH
Author-email: dk@ownly.de
License: MIT
Keywords: sms websms message text phone sender mobile
Platform: UNKNOWN
Classifier: Development Status :: 4 - Beta
Classifier: Intended Audience :: Developers
Classifier: License :: OSI Approved :: MIT License
Classifier: Operating System :: OS Independent
Classifier: Programming Language :: Python :: 3
Classifier: Programming Language :: Python :: 3.7
Classifier: Programming Language :: Python :: 3.8
Classifier: Programming Language :: Python :: 3.9
Classifier: Topic :: Utilities
License-File: LICENSE
